{
  "number": 111,
  "title_th": "พระเจ้าเป็นความรอดความสว่าง",
  "title_en": null,
  "theme": "พระคัมภีร์",
  "book_refs": [
    {
      "book": "ย",
      "no": 129
    }
  ],
  "scripture": "บพส.27:1,4,7-9ก,14",
  "content": {
    "version": 2,
    "key": "G",
    "timeSignature": "6/8",
    "stanzas": [
      {
        "id": "A",
        "lines": [
          [
            {
              "type": "segment",
              "chord": "",
              "note": ".5_"
            },
            {
              "type": "bar"
            },
            {
              "type": "segment",
              "chord": "G",
              "note": "3_ 3_ 3_"
            },
            {
              "type": "segment",
              "chord": "D",
              "note": "2_ 3_ 2_"
            },
            {
              "type": "bar"
            },
            {
              "type": "segment",
              "chord": "Em",
              "note": "1. 1."
            },
            {
              "type": "bar"
            },
            {
              "type": "segment",
              "chord": "C",
              "note": "4."
            },
            {
              "type": "segment",
              "chord": "G",
              "note": "3_ 2_ 3_"
            },
            {
              "type": "bar"
            },
            {
              "type": "segment",
              "chord": "D",
              "note": "2. 2"
            }
          ],
          [
            {
              "type": "segment",
              "chord": "",
              "note": ".5_"
            },
            {
              "type": "bar"
            },
            {
              "type": "segment",
              "chord": "C",
              "note": ".6_ .7_ 1_"
            },
            {
              "type": "segment",
              "chord": "G",
              "note": ".5 1_"
            },
            {
              "type": "bar"
            },
            {
              "type": "segment",
              "chord": "C",
              "note": ".6_ .7_ 1_"
            },
            {
              "type": "segment",
              "chord": "G",
              "note": ".5 1_"
            },
            {
              "type": "bar"
            },
            {
              "type": "segment",
              "chord": "C",
              "note": ".6_ .7_ 1_"
            },
            {
              "type": "segment",
              "chord": "D",
              "note": "2_ 1_ 2_"
            },
            {
              "type": "bar"
            },
            {
              "type": "segment",
              "chord": "G",
              "note": "1."
            },
            {
              "type": "segment",
              "chord": "D",
              "note": "0."
            },
            {
              "type": "bar"
            },
            {
              "type": "segment",
              "chord": "Em",
              "note": "0."
            },
            {
              "type": "segment",
              "chord": "D",
              "note": "0."
            }
          ]
        ]
      },
      {
        "id": "B",
        "lines": [
          [
            {
              "type": "segment",
              "chord": "G",
              "note": "3 3_"
            },
            {
              "type": "segment",
              "chord": "D",
              "note": "2_ 3_ 2_"
            },
            {
              "type": "bar"
            },
            {
              "type": "segment",
              "chord": "Em",
              "note": "1. .6."
            },
            {
              "type": "bar"
            },
            {
              "type": "segment",
              "chord": "C",
              "note": "4 4_"
            },
            {
              "type": "segment",
              "chord": "G",
              "note": "3_ 2_ 3_"
            },
            {
              "type": "bar"
            },
            {
              "type": "segment",
              "chord": "D",
              "note": "2. 2 .5_"
            },
            {
              "type": "bar"
            },
            {
              "type": "segment",
              "chord": "C",
              "note": ".6_ .7_ 1_"
            },
            {
              "type": "segment",
              "chord": "G",
              "note": ".5 1_"
            },
            {
              "type": "bar"
            },
            {
              "type": "segment",
              "chord": "C",
              "note": ".6_ .7_ 1_"
            },
            {
              "type": "segment",
              "chord": "G",
              "note": ".5"
            }
          ],
          [
            {
              "type": "segment",
              "chord": "",
              "note": "1_"
            },
            {
              "type": "bar"
            },
            {
              "type": "segment",
              "chord": "C",
              "note": ".6_ .7_ 1_"
            },
            {
              "type": "segment",
              "chord": "D",
              "note": "2_ 1_ 2_"
            },
            {
              "type": "bar"
            },
            {
              "type": "segment",
              "chord": "G",
              "note": "3_ 2_ 1_"
            },
            {
              "type": "segment",
              "chord": "D",
              "note": ".7_ 1_ 2_"
            },
            {
              "type": "bar"
            },
            {
              "type": "segment",
              "chord": "Em",
              "note": "1_ .7_ .6_"
            },
            {
              "type": "segment",
              "chord": "B",
              "note": ".#5_ .6_ .7_"
            },
            {
              "type": "bar"
            },
            {
              "type": "segment",
              "chord": "Em",
              "note": "1."
            }
          ],
          [
            {
              "type": "segment",
              "chord": "D",
              "note": "2_ 1_ 2_"
            },
            {
              "type": "bar"
            },
            {
              "type": "segment",
              "chord": "G",
              "note": "3_ 2_ 3_"
            },
            {
              "type": "segment",
              "chord": "D",
              "note": "4_ 3_ 2_"
            },
            {
              "type": "bar"
            },
            {
              "type": "segment",
              "chord": "G",
              "note": "1_ 1"
            },
            {
              "type": "segment",
              "chord": "D",
              "note": "0."
            },
            {
              "type": "bar"
            },
            {
              "type": "segment",
              "chord": "Em",
              "note": "0."
            },
            {
              "type": "segment",
              "chord": "D",
              "note": "0."
            }
          ]
        ]
      },
      {
        "id": "C",
        "lines": [
          [
            {
              "type": "segment",
              "chord": "G",
              "note": "3."
            },
            {
              "type": "segment",
              "chord": "D",
              "note": "2_ 3_ 2_"
            },
            {
              "type": "bar"
            },
            {
              "type": "segment",
              "chord": "Em",
              "note": "1. 1_ 2_ 3_"
            },
            {
              "type": "bar"
            },
            {
              "type": "segment",
              "chord": "C",
              "note": "4."
            },
            {
              "type": "segment",
              "chord": "G",
              "note": "3_ 2_ 3_"
            },
            {
              "type": "bar"
            },
            {
              "type": "segment",
              "chord": "D",
              "note": "2. 2 .5_"
            },
            {
              "type": "bar"
            },
            {
              "type": "segment",
              "chord": "C",
              "note": ".6_ .7_ 1_"
            },
            {
              "type": "segment",
              "chord": "G",
              "note": ".5 1_"
            },
            {
              "type": "bar"
            },
            {
              "type": "segment",
              "chord": "C",
              "note": ".6_ .7_ 1_"
            },
            {
              "type": "segment",
              "chord": "G",
              "note": ".5"
            }
          ],
          [
            {
              "type": "segment",
              "chord": "",
              "note": "1_"
            },
            {
              "type": "bar"
            },
            {
              "type": "segment",
              "chord": "C",
              "note": ".6_ .7_ 1_"
            },
            {
              "type": "segment",
              "chord": "D",
              "note": "2_ 1_ 2_"
            },
            {
              "type": "bar"
            },
            {
              "type": "segment",
              "chord": "G",
              "note": "1."
            },
            {
              "type": "segment",
              "chord": "D",
              "note": "0."
            },
            {
              "type": "bar"
            },
            {
              "type": "segment",
              "chord": "Em",
              "note": "0."
            },
            {
              "type": "segment",
              "chord": "D",
              "note": "0"
            }
          ]
        ]
      },
      {
        "id": "D",
        "lines": [
          [
            {
              "type": "segment",
              "chord": "G",
              "note": "3 3_"
            },
            {
              "type": "segment",
              "chord": "D",
              "note": "2_ 3_ 2_"
            },
            {
              "type": "bar"
            },
            {
              "type": "segment",
              "chord": "Em",
              "note": "1. 1_ 2_ 3_"
            },
            {
              "type": "bar"
            },
            {
              "type": "segment",
              "chord": "C",
              "note": "4 4_"
            },
            {
              "type": "segment",
              "chord": "G",
              "note": "3_ 2_ 3_"
            },
            {
              "type": "bar"
            },
            {
              "type": "segment",
              "chord": "D",
              "note": "2. 2"
            }
          ],
          [
            {
              "type": "segment",
              "chord": "",
              "note": ".5_"
            },
            {
              "type": "bar"
            },
            {
              "type": "segment",
              "chord": "C",
              "note": ".6_ .7_ 1_"
            },
            {
              "type": "segment",
              "chord": "G",
              "note": ".5 1_"
            },
            {
              "type": "bar"
            },
            {
              "type": "segment",
              "chord": "C",
              "note": ".6_ .7_ 1_"
            },
            {
              "type": "segment",
              "chord": "G",
              "note": ".5 1_"
            },
            {
              "type": "bar"
            },
            {
              "type": "segment",
              "chord": "C",
              "note": ".6_ .7_ 1_"
            },
            {
              "type": "segment",
              "chord": "D",
              "note": "2_ 1_ 2_"
            },
            {
              "type": "bar"
            },
            {
              "type": "segment",
              "chord": "G",
              "note": "1. 1"
            }
          ],
          [
            {
              "type": "segment",
              "chord": "",
              "note": ".5_"
            },
            {
              "type": "bar"
            },
            {
              "type": "segment",
              "chord": "C",
              "note": ".6_ .7_ 1_"
            },
            {
              "type": "segment",
              "chord": "D",
              "note": "2_ 1_ 2_"
            },
            {
              "type": "bar"
            },
            {
              "type": "segment",
              "chord": "G",
              "note": "1. 1 0_"
            },
            {
              "type": "bar"
            },
            {
              "type": "segment",
              "chord": "G",
              "note": "0. 0"
            }
          ],
          [
            {
              "type": "segment",
              "chord": "",
              "note": "2 7 1"
            },
            {
              "type": "bar"
            },
            {
              "type": "segment",
              "chord": "",
              "note": "4 7 -"
            },
            {
              "type": "bar"
            },
            {
              "type": "segment",
              "chord": "",
              "note": "1 4"
            }
          ]
        ]
      }
    ],
    "arrangement": [
      {
        "stanza": "A",
        "label": "ร้อง 1",
        "syllables": [
          "พระ",
          "เจ้า",
          "เป็น",
          "ความ",
          "รอด",
          "ความ",
          "สว่าง",
          "ข้า",
          "ต้อง",
          "กลัว",
          "ผู้",
          "ใด",
          "?",
          "ทรง",
          "เป็น",
          "กำ",
          "-ลัง",
          "ชี",
          "วิ",
          "ต",
          "ยิ่ง",
          "ใหญ่",
          "ข้า",
          "ยัง",
          "จะ",
          "ต้อง",
          "ไป",
          "กลัว",
          "ใคร",
          "?",
          "",
          "",
          "",
          "",
          "",
          ""
        ]
      },
      {
        "stanza": "B",
        "label": "ร้อง 2",
        "syllables": [
          "สิ่ง",
          "เดียว",
          "ข้า",
          "ขอ",
          "จาก",
          "พระ",
          "องค์",
          "แล้ว",
          "ข้า",
          "จะ",
          "เสาะ",
          "หา",
          "คือ",
          "ได้",
          "อา",
          "ศัย",
          "ใน",
          "วิ",
          "หาร",
          "มั่น",
          "คง",
          "ต",
          "ลอด",
          "สืบ",
          "ไป",
          "ชั่ว",
          "ชี",
          "วิ",
          "ต",
          "ของ",
          "ข้า",
          "เพื่อ",
          "เห็น",
          "สง่า",
          "พระ",
          "ยะ",
          "โฮ",
          "วา",
          "และ",
          "ได้",
          "พิ",
          "-นิ",
          "ศ",
          "พระ",
          "วิ",
          "หาร",
          "งาม",
          "ตา",
          ".",
          "",
          "",
          "",
          "",
          "",
          "",
          "",
          ""
        ]
      },
      {
        "stanza": "C",
        "label": "ร้อง 3",
        "syllables": [
          "พระ",
          "-ยะ",
          "โฮ",
          "วา",
          "โปรด",
          "ส",
          "-ดับ",
          "เสียง",
          "ร้อง",
          "ข้า",
          "พระ",
          "-องค์",
          "เจ้า",
          "ข้า",
          "โปรด",
          "ก",
          "รุ",
          "-ณา",
          "ขอ",
          "โปรด",
          "ดำ",
          "รัส",
          "ตรัส",
          "ตอบ",
          "ข้า",
          ".",
          "",
          "",
          "",
          "",
          "",
          "",
          "",
          "",
          ""
        ]
      },
      {
        "stanza": "A",
        "label": "ร้อง 4",
        "syllables": [
          "“",
          "พระ",
          "พักตร์",
          "เรา",
          "เจ้า",
          "จง",
          "เสาะ",
          "หา",
          "”",
          "ใจ",
          "ข้า",
          "ทูล",
          "ตอบ",
          "ว่า",
          "จิต",
          "ข้า",
          "เสาะ",
          "หา",
          "พระ",
          "พักตร์",
          "ส",
          "ง่า",
          "อย่า",
          "ซ่อน",
          "พระ",
          "พักตร์",
          "จาก",
          "ข้า",
          ".",
          "",
          "",
          "",
          "",
          "",
          "",
          ""
        ]
      },
      {
        "stanza": "D",
        "label": "ร้อง 5",
        "syllables": [
          "สิ่ง",
          "ที่",
          "รู้",
          "แน่",
          "คือ",
          "ว่า",
          "ข้า",
          "จะ",
          "คอย",
          "ท่า",
          "พระ",
          "ยะ",
          "โฮ",
          "วา",
          "ต",
          "ลอด",
          "ชี",
          "วา",
          "ข้า",
          "ใน",
          "โล",
          "-กา",
          "ตั้ง",
          "ข้อ",
          "ให้",
          "แข็ง",
          "ใจ",
          "แกร่ง",
          "กล้า",
          "จง",
          "คอย",
          "ท่า",
          "พระ",
          "ยะ",
          "โฮ",
          "วา",
          ".",
          "",
          "",
          "",
          "",
          "",
          "",
          "",
          "",
          "",
          "",
          "",
          "",
          "",
          "",
          "",
          "",
          "",
          ""
        ]
      }
    ]
  },
  "_warnings": [
    "PDF systems (13) != DOCX staves (12) — structure may drift; verify",
    "system 12: repeat/volta markers [(320.23, '║')] — NEEDS manual repeat/volta",
    "system 13: no printed barlines — bars inferred by beat count (verify)",
    "system 13: repeat/volta markers [(294.28424, ':')] — NEEDS manual repeat/volta",
    "system ร้อง1: 30 syllables vs 33 attack notes",
    "system ร้อง2: 49 syllables vs 54 attack notes",
    "system ร้อง3: 26 syllables vs 32 attack notes",
    "system ร้อง4: 29 syllables vs 33 attack notes",
    "system ร้อง5: 37 syllables vs 51 attack notes"
  ]
}